optweights/__init__.py
optweights/metrics.py
optweights/model.py
optweights/utils.py
optweights/weight_searcher.py
optweights/weights.py
optweights-0.1.0.dist-info/METADATA
optweights-0.1.0.dist-info/WHEEL
optweights-0.1.0.dist-info/top_level.txt
optweights-0.1.0.dist-info/RECORD
